{
    "My Feature": {
        "should have a passing test": "PASSED",
        "might have a failing test": "FAILED",
        "minght have another unfulfilled test": "PASSED",
        "might have an unfulfilled test": "PASSED"
    },
    "My Feature My Context": {
        "should have a passing test": "PASSED",
        "might have a failing test": "FAILED",
        "minght have another unfulfilled test": "PASSED",
        "might have an unfulfilled test": "PASSED"
    },
    "My Feature My context": {
        "should have a passing test": "PASSED",
        "might have a failing test": "FAILED",
        "minght have another unfulfilled test": "PASSED",
        "might have an unfulfilled test": "PASSED"
    }
}